expipe/__init__.py
expipe/__main__.py
expipe/backend.py
expipe/cli.py
expipe/config.py
expipe/core.py
expipe/version.py
expipe/backends/__init__.py
expipe/backends/filesystem.py
expipe/cliutils/__init__.py
expipe/cliutils/misc.py
expipe/cliutils/plugin.py
expipe/widgets/__init__.py
expipe/widgets/browser.py
expipe/widgets/display.py
expipe-0.6.0.dist-info/LICENSE
expipe-0.6.0.dist-info/METADATA
expipe-0.6.0.dist-info/WHEEL
expipe-0.6.0.dist-info/entry_points.txt
expipe-0.6.0.dist-info/top_level.txt
expipe-0.6.0.dist-info/RECORD
