Metadata-Version: 2.1
Name: expipe
Version: 0.6.0
Summary: Experiment-data management platform
Home-page: https://github.com/CINPLA/expipe
Author: CINPLA
Author-email: 
Maintainer: Mikkel Elle Lepperød
Maintainer-email: m.e.lepperod@medisin.uio.no
Platform: Linux
Platform: Windows
Classifier: Intended Audience :: Science/Research
Classifier: License :: OSI Approved :: GNU General Public License v2 (GPLv2)
Classifier: Natural Language :: English
Classifier: Programming Language :: Python :: 3
Classifier: Topic :: Scientific/Engineering
Requires-Python: >=3.9
License-File: LICENSE
Requires-Dist: numpy >=1.25
Requires-Dist: ruamel.yaml >=0.18.5
Requires-Dist: quantities >=0.14.1
Requires-Dist: pandas >=2.1.2
Requires-Dist: ipywidgets >=8.1.1
Requires-Dist: click >=8.1.7
